hirez_api_wrapper.py
hirez_api_wrapper-1.0.3.dist-info/LICENSE.rst
hirez_api_wrapper-1.0.3.dist-info/METADATA
hirez_api_wrapper-1.0.3.dist-info/WHEEL
hirez_api_wrapper-1.0.3.dist-info/top_level.txt
hirez_api_wrapper-1.0.3.dist-info/RECORD
